pyhttpintercept/__init__.py
pyhttpintercept/_constants.py
pyhttpintercept/_metadata.py
pyhttpintercept/exceptions.py
pyhttpintercept/config/__init__.py
pyhttpintercept/config/constants.py
pyhttpintercept/config/hosting.py
pyhttpintercept/config/https_domains.py
pyhttpintercept/config/intercept.py
pyhttpintercept/config/intercept_handlers.py
pyhttpintercept/config/intercept_scenarios.py
pyhttpintercept/config/persistent_fields.py
pyhttpintercept/config/redirect.py
pyhttpintercept/gui/__init__.py
pyhttpintercept/gui/support.py
pyhttpintercept/gui/frame/__init__.py
pyhttpintercept/gui/frame/http_server_config.py
pyhttpintercept/gui/frame/https_allowed_domains.py
pyhttpintercept/gui/frame/https_domain.py
pyhttpintercept/gui/frame/redirect_uri.py
pyhttpintercept/gui/frame/redirect_uris.py
pyhttpintercept/gui/frame/scenario.py
pyhttpintercept/gui/frame/scenarios.py
pyhttpintercept/gui/frame/server.py
pyhttpintercept/gui/frame/server_config.py
pyhttpintercept/gui/frame/ssl_config.py
pyhttpintercept/gui/window/__init__.py
pyhttpintercept/gui/window/http_server_config.py
pyhttpintercept/gui/window/https_allowed_domains.py
pyhttpintercept/gui/window/https_domain.py
pyhttpintercept/gui/window/redirect_uri.py
pyhttpintercept/gui/window/redirect_uris.py
pyhttpintercept/gui/window/scenario.py
pyhttpintercept/gui/window/scenarios.py
pyhttpintercept/gui/window/server.py
pyhttpintercept/gui/window/server_config.py
pyhttpintercept/gui/window/ssl_config.py
pyhttpintercept/helpers/__init__.py
pyhttpintercept/helpers/compression.py
pyhttpintercept/helpers/encoding.py
pyhttpintercept/helpers/testing.py
pyhttpintercept/hosting/__init__.py
pyhttpintercept/hosting/hosting.py
pyhttpintercept/intercept/__init__.py
pyhttpintercept/intercept/_handler.py
pyhttpintercept/intercept/_modifier.py
pyhttpintercept/intercept/_scenario.py
pyhttpintercept/intercept/_updater.py
pyhttpintercept/intercept/intercept.py
pyhttpintercept/intercept/handlers/__init__.py
pyhttpintercept-0.34.1.dist-info/LICENSE.txt
pyhttpintercept-0.34.1.dist-info/METADATA
pyhttpintercept-0.34.1.dist-info/WHEEL
pyhttpintercept-0.34.1.dist-info/entry_points.txt
pyhttpintercept-0.34.1.dist-info/top_level.txt
pyhttpintercept-0.34.1.dist-info/RECORD
