Metadata-Version: 2.1
Name: pyhttpintercept
Version: 0.34.1
Summary: UNKNOWN
Home-page: https://bitbucket.org/davisowb/pyhttpintercept.git
Author: Oli Davis & Hywel Thomas
Author-email: oli.davis@me.com, hywel.thomas@mac.com
License: MIT
Download-URL: https://bitbucket.org/davisowb/pyhttpintercept.git/get/0.34.1.tar
Keywords: pyhttpintercept
Platform: UNKNOWN
Classifier: Development Status :: 3 - Alpha
Classifier: Intended Audience :: Developers
Classifier: License :: OSI Approved :: MIT License
Classifier: Programming Language :: Python :: 2
Classifier: Programming Language :: Python :: 2.7
Classifier: Programming Language :: Python :: 3
Classifier: Programming Language :: Python :: 3.6
Classifier: Topic :: Utilities
License-File: LICENSE.txt
Requires-Dist: future (>=0.16.0)
Requires-Dist: attrs (>=16.3.0)
Requires-Dist: requests (>=2.11.1)
Requires-Dist: cryptography (>=2.2.1)
Requires-Dist: apiutil (>=1.6.4)
Requires-Dist: logging-helper (>=1.8.4)
Requires-Dist: fdutil (>=1.15.0)
Requires-Dist: networkutil (>=1.19.4)
Requires-Dist: configurationutil[ui] (>=3.3.1)
Requires-Dist: tableutil (>=2.4.0)
Requires-Dist: uiutil (>=1.35.0)
Requires-Dist: classutils (>=1.11.3)
Requires-Dist: timingsutil (>=1.2.0)
Requires-Dist: simpil (>=1.1.1)
Requires-Dist: Pillow (>=5.3.0)
Provides-Extra: test
